[
  {
    "id": "2",
    "y_2010": "164103"
  },
  {
    "id": "3",
    "y_2010": "345761"
  },
  {
    "id": "4",
    "y_2010": "711454"
  },
  {
    "id": "5",
    "y_2010": "64945"
  },
  {
    "id": "6",
    "y_2010": "71001"
  },
  {
    "id": "7",
    "y_2010": "1334180"
  },
  {
    "id": "8",
    "y_2010": "219654"
  },
  {
    "id": "9",
    "y_2010": "175070"
  },
  {
    "id": "10",
    "y_2010": "101044"
  },
  {
    "id": "11",
    "y_2010": "392996"
  },
  {
    "id": "12",
    "y_2010": "31429"
  },
  {
    "id": "13",
    "y_2010": "160875"
  },
  {
    "id": "14",
    "y_2010": "142289"
  },
  {
    "id": "15",
    "y_2010": "253312"
  },
  {
    "id": "16",
    "y_2010": "103307"
  },
  {
    "id": "17",
    "y_2010": "94158"
  },
  {
    "id": "18",
    "y_2010": "567314"
  },
  {
    "id": "19",
    "y_2010": "221995"
  },
  {
    "id": "20",
    "y_2010": "190167"
  },
  {
    "id": "21",
    "y_2010": "107275"
  },
  {
    "id": "22",
    "y_2010": "105223"
  },
  {
    "id": "23",
    "y_2010": "110871"
  },
  {
    "id": "24",
    "y_2010": "205065"
  },
  {
    "id": "25",
    "y_2010": "279979"
  },
  {
    "id": "26",
    "y_2010": "162435"
  },
  {
    "id": "27",
    "y_2010": "117421"
  },
  {
    "id": "28",
    "y_2010": "437164"
  },
  {
    "id": "29",
    "y_2010": "224405"
  },
  {
    "id": "30",
    "y_2010": "56104"
  },
  {
    "id": "31",
    "y_2010": "371686"
  },
  {
    "id": "32",
    "y_2010": "99414"
  },
  {
    "id": "33",
    "y_2010": "140508"
  },
  {
    "id": "34",
    "y_2010": "73893"
  },
  {
    "id": "35",
    "y_2010": "152379"
  },
  {
    "id": "36",
    "y_2010": "150764"
  },
  {
    "id": "37",
    "y_2010": "94060"
  },
  {
    "id": "38",
    "y_2010": "190731"
  },
  {
    "id": "39",
    "y_2010": "128459"
  },
  {
    "id": "40",
    "y_2010": "82893"
  },
  {
    "id": "41",
    "y_2010": "104373"
  },
  {
    "id": "42",
    "y_2010": "200484"
  },
  {
    "id": "43",
    "y_2010": "349478"
  },
  {
    "id": "44",
    "y_2010": "853374"
  },
  {
    "id": "45",
    "y_2010": "216723"
  },
  {
    "id": "46",
    "y_2010": "119532"
  },
  {
    "id": "47",
    "y_2010": "347643"
  },
  {
    "id": "48",
    "y_2010": "129480"
  },
  {
    "id": "49",
    "y_2010": "117959"
  },
  {
    "id": "50",
    "y_2010": "84499"
  },
  {
    "id": "51",
    "y_2010": "198859"
  },
  {
    "id": "52",
    "y_2010": "121630"
  },
  {
    "id": "53",
    "y_2010": "67064"
  },
  {
    "id": "54",
    "y_2010": "79625"
  },
  {
    "id": "55",
    "y_2010": "214201"
  },
  {
    "id": "56",
    "y_2010": "197664"
  },
  {
    "id": "57",
    "y_2010": "64892"
  },
  {
    "id": "58",
    "y_2010": "113514"
  },
  {
    "id": "59",
    "y_2010": "96649"
  },
  {
    "id": "60",
    "y_2010": "78106"
  },
  {
    "id": "61",
    "y_2010": "119626"
  },
  {
    "id": "62",
    "y_2010": ""
  },
  {
    "id": "63",
    "y_2010": ""
  },
  {
    "id": "64",
    "y_2010": "60149"
  },
  {
    "id": "65",
    "y_2010": "266967"
  },
  {
    "id": "66",
    "y_2010": "110013"
  },
  {
    "id": "67",
    "y_2010": "102800"
  },
  {
    "id": "68",
    "y_2010": "133298"
  },
  {
    "id": "69",
    "y_2010": "692517"
  },
  {
    "id": "70",
    "y_2010": "45376"
  },
  {
    "id": "71",
    "y_2010": "133878"
  },
  {
    "id": "72",
    "y_2010": "131038"
  },
  {
    "id": "73",
    "y_2010": "118222"
  },
  {
    "id": "74",
    "y_2010": "118426"
  },
  {
    "id": "75",
    "y_2010": "292276"
  },
  {
    "id": "76",
    "y_2010": "203979"
  },
  {
    "id": "77",
    "y_2010": "150183"
  },
  {
    "id": "78",
    "y_2010": "151890"
  },
  {
    "id": "79",
    "y_2010": ""
  },
  {
    "id": "80",
    "y_2010": "110702"
  },
  {
    "id": "81",
    "y_2010": "145742"
  },
  {
    "id": "82",
    "y_2010": "163123"
  },
  {
    "id": "83",
    "y_2010": "256706"
  },
  {
    "id": "84",
    "y_2010": "130847"
  },
  {
    "id": "85",
    "y_2010": "43687"
  },
  {
    "id": "86",
    "y_2010": "65374"
  },
  {
    "id": "87",
    "y_2010": "142935"
  },
  {
    "id": "88",
    "y_2010": "68124"
  },
  {
    "id": "89",
    "y_2010": "93738"
  },
  {
    "id": "90",
    "y_2010": "116746"
  },
  {
    "id": "91",
    "y_2010": "96291"
  },
  {
    "id": "92",
    "y_2010": "191616"
  },
  {
    "id": "93",
    "y_2010": "187500"
  },
  {
    "id": "94",
    "y_2010": "77941"
  },
  {
    "id": "95",
    "y_2010": "152964"
  },
  {
    "id": "96",
    "y_2010": "129437"
  },
  {
    "id": "97",
    "y_2010": "149824"
  },
  {
    "id": "98",
    "y_2010": "137927"
  },
  {
    "id": "99",
    "y_2010": "154158"
  },
  {
    "id": "100",
    "y_2010": "75875"
  },
  {
    "id": "101",
    "y_2010": "97528"
  },
  {
    "id": "102",
    "y_2010": "85976"
  },
  {
    "id": "103",
    "y_2010": "45578"
  },
  {
    "id": "104",
    "y_2010": "76792"
  },
  {
    "id": "105",
    "y_2010": "180923"
  },
  {
    "id": "106",
    "y_2010": "210037"
  },
  {
    "id": "107",
    "y_2010": "106173"
  },
  {
    "id": "108",
    "y_2010": "133322"
  },
  {
    "id": "109",
    "y_2010": "346752"
  },
  {
    "id": "110",
    "y_2010": "212286"
  },
  {
    "id": "111",
    "y_2010": "157403"
  },
  {
    "id": "112",
    "y_2010": "143436"
  },
  {
    "id": "113",
    "y_2010": "95455"
  },
  {
    "id": "114",
    "y_2010": "80342"
  },
  {
    "id": "115",
    "y_2010": "285088"
  },
  {
    "id": "116",
    "y_2010": "126971"
  },
  {
    "id": "117",
    "y_2010": "106938"
  },
  {
    "id": "118",
    "y_2010": "296713"
  },
  {
    "id": "119",
    "y_2010": "99347"
  },
  {
    "id": "120",
    "y_2010": "79925"
  },
  {
    "id": "121",
    "y_2010": "82860"
  },
  {
    "id": "122",
    "y_2010": "143300"
  },
  {
    "id": "123",
    "y_2010": "59197"
  },
  {
    "id": "124",
    "y_2010": "73792"
  },
  {
    "id": "125",
    "y_2010": "85894"
  },
  {
    "id": "126",
    "y_2010": "56880"
  },
  {
    "id": "127",
    "y_2010": "113514"
  },
  {
    "id": "128",
    "y_2010": "72938"
  },
  {
    "id": "129",
    "y_2010": "270093"
  },
  {
    "id": "130",
    "y_2010": "429584"
  },
  {
    "id": "131",
    "y_2010": "123012"
  },
  {
    "id": "132",
    "y_2010": "180233"
  },
  {
    "id": "133",
    "y_2010": "265717"
  },
  {
    "id": "134",
    "y_2010": "102150"
  },
  {
    "id": "135",
    "y_2010": "60811"
  },
  {
    "id": "136",
    "y_2010": "162469"
  },
  {
    "id": "137",
    "y_2010": "99483"
  },
  {
    "id": "138",
    "y_2010": "72820"
  },
  {
    "id": "139",
    "y_2010": "78096"
  },
  {
    "id": "140",
    "y_2010": "101185"
  },
  {
    "id": "141",
    "y_2010": "56932"
  },
  {
    "id": "142",
    "y_2010": "79561"
  },
  {
    "id": "143",
    "y_2010": "357723"
  },
  {
    "id": "144",
    "y_2010": "102449"
  },
  {
    "id": "145",
    "y_2010": "96531"
  },
  {
    "id": "146",
    "y_2010": "126013"
  },
  {
    "id": "147",
    "y_2010": "97266"
  },
  {
    "id": "148",
    "y_2010": "353041"
  },
  {
    "id": "149",
    "y_2010": "173618"
  },
  {
    "id": "150",
    "y_2010": "112058"
  },
  {
    "id": "151",
    "y_2010": "261358"
  },
  {
    "id": "152",
    "y_2010": "129322"
  },
  {
    "id": "153",
    "y_2010": "223934"
  },
  {
    "id": "154",
    "y_2010": "172866"
  },
  {
    "id": "155",
    "y_2010": "126804"
  },
  {
    "id": "156",
    "y_2010": "92251"
  },
  {
    "id": "157",
    "y_2010": "101697"
  },
  {
    "id": "158",
    "y_2010": "74765"
  },
  {
    "id": "159",
    "y_2010": "74415"
  },
  {
    "id": "160",
    "y_2010": "89004"
  },
  {
    "id": "161",
    "y_2010": "550618"
  },
  {
    "id": "162",
    "y_2010": "99774"
  },
  {
    "id": "163",
    "y_2010": "206032"
  },
  {
    "id": "164",
    "y_2010": "130790"
  },
  {
    "id": "165",
    "y_2010": "84046"
  },
  {
    "id": "166",
    "y_2010": "80522"
  },
  {
    "id": "167",
    "y_2010": "117507"
  },
  {
    "id": "168",
    "y_2010": "78877"
  },
  {
    "id": "169",
    "y_2010": "219011"
  },
  {
    "id": "170",
    "y_2010": "286537"
  },
  {
    "id": "171",
    "y_2010": "302201"
  },
  {
    "id": "172",
    "y_2010": "284171"
  },
  {
    "id": "173",
    "y_2010": "67322"
  },
  {
    "id": "174",
    "y_2010": "146700"
  },
  {
    "id": "175",
    "y_2010": "251721"
  },
  {
    "id": "176",
    "y_2010": "231713"
  },
  {
    "id": "177",
    "y_2010": "288898"
  },
  {
    "id": "178",
    "y_2010": "108945"
  },
  {
    "id": "179",
    "y_2010": "339894"
  },
  {
    "id": "180",
    "y_2010": "110909"
  },
  {
    "id": "181",
    "y_2010": "343127"
  },
  {
    "id": "182",
    "y_2010": "104882"
  },
  {
    "id": "183",
    "y_2010": "100006"
  },
  {
    "id": "184",
    "y_2010": "211180"
  },
  {
    "id": "185",
    "y_2010": "62400"
  },
  {
    "id": "186",
    "y_2010": "98420"
  },
  {
    "id": "187",
    "y_2010": "270553"
  },
  {
    "id": "188",
    "y_2010": "237689"
  },
  {
    "id": "189",
    "y_2010": "622115"
  },
  {
    "id": "190",
    "y_2010": "74310"
  },
  {
    "id": "191",
    "y_2010": "124021"
  },
  {
    "id": "192",
    "y_2010": "184500"
  },
  {
    "id": "193",
    "y_2010": "384172"
  },
  {
    "id": "194",
    "y_2010": "491090"
  },
  {
    "id": "195",
    "y_2010": "196628"
  },
  {
    "id": "196",
    "y_2010": "104183"
  },
  {
    "id": "197",
    "y_2010": "100727"
  },
  {
    "id": "198",
    "y_2010": "297814"
  },
  {
    "id": "199",
    "y_2010": "97149"
  },
  {
    "id": "200",
    "y_2010": "140300"
  },
  {
    "id": "201",
    "y_2010": "549220"
  },
  {
    "id": "202",
    "y_2010": "99539"
  },
  {
    "id": "203",
    "y_2010": "182644"
  },
  {
    "id": "204",
    "y_2010": "199645"
  },
  {
    "id": "205",
    "y_2010": "464739"
  },
  {
    "id": "206",
    "y_2010": "283606"
  },
  {
    "id": "207",
    "y_2010": "313710"
  },
  {
    "id": "208",
    "y_2010": "903950"
  },
  {
    "id": "209",
    "y_2010": "116107"
  },
  {
    "id": "210",
    "y_2010": "303333"
  },
  {
    "id": "211",
    "y_2010": "115424"
  },
  {
    "id": "212",
    "y_2010": "109803"
  },
  {
    "id": "213",
    "y_2010": "270409"
  },
  {
    "id": "215",
    "y_2010": "615944"
  },
  {
    "id": "216",
    "y_2010": "564603"
  },
  {
    "id": "217",
    "y_2010": "653587"
  },
  {
    "id": "218",
    "y_2010": "157462"
  },
  {
    "id": "219",
    "y_2010": "105674"
  },
  {
    "id": "220",
    "y_2010": "108019"
  },
  {
    "id": "221",
    "y_2010": "139864"
  },
  {
    "id": "222",
    "y_2010": "246722"
  },
  {
    "id": "223",
    "y_2010": "93596"
  },
  {
    "id": "224",
    "y_2010": "221402"
  },
  {
    "id": "225",
    "y_2010": "151344"
  },
  {
    "id": "226",
    "y_2010": "198392"
  },
  {
    "id": "227",
    "y_2010": "123457"
  },
  {
    "id": "228",
    "y_2010": "141612"
  },
  {
    "id": "229",
    "y_2010": "122656"
  },
  {
    "id": "230",
    "y_2010": "50634"
  },
  {
    "id": "231",
    "y_2010": "147888"
  },
  {
    "id": "232",
    "y_2010": "124545"
  },
  {
    "id": "233",
    "y_2010": "268474"
  },
  {
    "id": "234",
    "y_2010": "137486"
  },
  {
    "id": "235",
    "y_2010": "270588"
  },
  {
    "id": "236",
    "y_2010": "959107"
  },
  {
    "id": "237",
    "y_2010": "106764"
  },
  {
    "id": "238",
    "y_2010": "101804"
  },
  {
    "id": "240",
    "y_2010": "134737"
  },
  {
    "id": "241",
    "y_2010": "495418"
  },
  {
    "id": "242",
    "y_2010": "130796"
  },
  {
    "id": "243",
    "y_2010": "190799"
  },
  {
    "id": "244",
    "y_2010": "130894"
  },
  {
    "id": "245",
    "y_2010": "136251"
  },
  {
    "id": "246",
    "y_2010": "88711"
  },
  {
    "id": "247",
    "y_2010": "137040"
  },
  {
    "id": "248",
    "y_2010": "60300"
  },
  {
    "id": "249",
    "y_2010": "82283"
  },
  {
    "id": "250",
    "y_2010": "125021"
  },
  {
    "id": "251",
    "y_2010": "173167"
  },
  {
    "id": "252",
    "y_2010": "170287"
  },
  {
    "id": "253",
    "y_2010": "264375"
  },
  {
    "id": "254",
    "y_2010": "126556"
  },
  {
    "id": "255",
    "y_2010": "274401"
  },
  {
    "id": "256",
    "y_2010": "428389"
  },
  {
    "id": "257",
    "y_2010": "199235"
  },
  {
    "id": "258",
    "y_2010": "98876"
  },
  {
    "id": "259",
    "y_2010": "104640"
  },
  {
    "id": "260",
    "y_2010": "98987"
  },
  {
    "id": "261",
    "y_2010": "145684"
  },
  {
    "id": "262",
    "y_2010": "411690"
  },
  {
    "id": "263",
    "y_2010": "293989"
  },
  {
    "id": "264",
    "y_2010": "162007"
  },
  {
    "id": "265",
    "y_2010": "147374"
  },
  {
    "id": "266",
    "y_2010": "133257"
  },
  {
    "id": "267",
    "y_2010": "155586"
  },
  {
    "id": "268",
    "y_2010": "108120"
  },
  {
    "id": "269",
    "y_2010": "276668"
  },
  {
    "id": "270",
    "y_2010": ""
  },
  {
    "id": "271",
    "y_2010": "87235"
  },
  {
    "id": "272",
    "y_2010": ""
  },
  {
    "id": "273",
    "y_2010": "130062"
  },
  {
    "id": "274",
    "y_2010": ""
  },
  {
    "id": "275",
    "y_2010": "227634"
  },
  {
    "id": "276",
    "y_2010": "159043"
  },
  {
    "id": "277",
    "y_2010": "152538"
  },
  {
    "id": "278",
    "y_2010": "145953"
  },
  {
    "id": "279",
    "y_2010": "101819"
  },
  {
    "id": "280",
    "y_2010": "96164"
  },
  {
    "id": "281",
    "y_2010": "120799"
  },
  {
    "id": "282",
    "y_2010": "113831"
  },
  {
    "id": "283",
    "y_2010": "109777"
  },
  {
    "id": "284",
    "y_2010": "479288"
  },
  {
    "id": "285",
    "y_2010": "162022"
  },
  {
    "id": "286",
    "y_2010": "94916"
  },
  {
    "id": "287",
    "y_2010": "167746"
  },
  {
    "id": "288",
    "y_2010": "236927"
  },
  {
    "id": "289",
    "y_2010": "158627"
  },
  {
    "id": "290",
    "y_2010": "76607"
  },
  {
    "id": "291",
    "y_2010": "52461"
  },
  {
    "id": "292",
    "y_2010": "72257"
  },
  {
    "id": "293",
    "y_2010": "73638"
  },
  {
    "id": "294",
    "y_2010": "72985"
  },
  {
    "id": "295",
    "y_2010": "81926"
  },
  {
    "id": "296",
    "y_2010": "188270"
  },
  {
    "id": "297",
    "y_2010": "409616"
  },
  {
    "id": "298",
    "y_2010": "71766"
  },
  {
    "id": "299",
    "y_2010": "101850"
  },
  {
    "id": "300",
    "y_2010": "213894"
  },
  {
    "id": "301",
    "y_2010": "132242"
  },
  {
    "id": "302",
    "y_2010": "269790"
  },
  {
    "id": "303",
    "y_2010": "241189"
  },
  {
    "id": "304",
    "y_2010": "74250"
  },
  {
    "id": "305",
    "y_2010": "91356"
  },
  {
    "id": "306",
    "y_2010": "88528"
  },
  {
    "id": "307",
    "y_2010": "113153"
  },
  {
    "id": "308",
    "y_2010": "213289"
  },
  {
    "id": "309",
    "y_2010": "246895"
  },
  {
    "id": "310",
    "y_2010": "204671"
  },
  {
    "id": "311",
    "y_2010": "72618"
  },
  {
    "id": "312",
    "y_2010": "88188"
  },
  {
    "id": "313",
    "y_2010": "122475"
  },
  {
    "id": "314",
    "y_2010": "130083"
  },
  {
    "id": "315",
    "y_2010": "210226"
  },
  {
    "id": "316",
    "y_2010": "98104"
  },
  {
    "id": "317",
    "y_2010": "75842"
  },
  {
    "id": "318",
    "y_2010": "188770"
  },
  {
    "id": "319",
    "y_2010": "114593"
  },
  {
    "id": "320",
    "y_2010": "295438"
  },
  {
    "id": "321",
    "y_2010": "50961"
  },
  {
    "id": "322",
    "y_2010": "116900"
  },
  {
    "id": "323",
    "y_2010": "101536"
  },
  {
    "id": "324",
    "y_2010": "235994"
  },
  {
    "id": "325",
    "y_2010": "113048"
  },
  {
    "id": "326",
    "y_2010": "71216"
  },
  {
    "id": "327",
    "y_2010": "72486"
  },
  {
    "id": "328",
    "y_2010": "114994"
  },
  {
    "id": "329",
    "y_2010": "117041"
  },
  {
    "id": "330",
    "y_2010": "96216"
  },
  {
    "id": "331",
    "y_2010": "121083"
  },
  {
    "id": "332",
    "y_2010": "126798"
  },
  {
    "id": "333",
    "y_2010": "93151"
  },
  {
    "id": "334",
    "y_2010": ""
  },
  {
    "id": "335",
    "y_2010": "251549"
  },
  {
    "id": "336",
    "y_2010": "189403"
  },
  {
    "id": "337",
    "y_2010": "217460"
  },
  {
    "id": "338",
    "y_2010": ""
  },
  {
    "id": "339",
    "y_2010": "236682"
  },
  {
    "id": "340",
    "y_2010": "258503"
  },
  {
    "id": "341",
    "y_2010": "220804"
  },
  {
    "id": "342",
    "y_2010": "651012"
  },
  {
    "id": "343",
    "y_2010": "206385"
  },
  {
    "id": "344",
    "y_2010": "130622"
  },
  {
    "id": "345",
    "y_2010": "120663"
  },
  {
    "id": "346",
    "y_2010": "77403"
  },
  {
    "id": "347",
    "y_2010": "130549"
  },
  {
    "id": "348",
    "y_2010": "124597"
  },
  {
    "id": "349",
    "y_2010": "697038"
  },
  {
    "id": "350",
    "y_2010": "296076"
  },
  {
    "id": "351",
    "y_2010": "306149"
  },
  {
    "id": "352",
    "y_2010": "249658"
  },
  {
    "id": "353",
    "y_2010": "288676"
  },
  {
    "id": "354",
    "y_2010": "128309"
  },
  {
    "id": "355",
    "y_2010": "226937"
  },
  {
    "id": "356",
    "y_2010": "445687"
  },
  {
    "id": "357",
    "y_2010": "216591"
  },
  {
    "id": "358",
    "y_2010": "343117"
  },
  {
    "id": "359",
    "y_2010": "401020"
  },
  {
    "id": "360",
    "y_2010": "130369"
  },
  {
    "id": "361",
    "y_2010": "76565"
  },
  {
    "id": "362",
    "y_2010": "71176"
  },
  {
    "id": "363",
    "y_2010": "50897"
  },
  {
    "id": "364",
    "y_2010": "915991"
  },
  {
    "id": "365",
    "y_2010": "132203"
  },
  {
    "id": "366",
    "y_2010": "140974"
  },
  {
    "id": "367",
    "y_2010": "271162"
  },
  {
    "id": "368",
    "y_2010": "116780"
  },
  {
    "id": "369",
    "y_2010": "75044"
  },
  {
    "id": "370",
    "y_2010": "62444"
  },
  {
    "id": "371",
    "y_2010": "82520"
  },
  {
    "id": "372",
    "y_2010": "180934"
  },
  {
    "id": "373",
    "y_2010": "297574"
  },
  {
    "id": "374",
    "y_2010": "69290"
  },
  {
    "id": "375",
    "y_2010": "623528"
  },
  {
    "id": "376",
    "y_2010": "103261"
  },
  {
    "id": "377",
    "y_2010": "154410"
  },
  {
    "id": "378",
    "y_2010": "282587"
  },
  {
    "id": "379",
    "y_2010": "450605"
  },
  {
    "id": "380",
    "y_2010": "409894"
  },
  {
    "id": "381",
    "y_2010": "200165"
  },
  {
    "id": "382",
    "y_2010": "93111"
  },
  {
    "id": "383",
    "y_2010": "156706"
  },
  {
    "id": "384",
    "y_2010": "241652"
  },
  {
    "id": "385",
    "y_2010": "65150"
  },
  {
    "id": "386",
    "y_2010": "120572"
  },
  {
    "id": "387",
    "y_2010": "78013"
  },
  {
    "id": "388",
    "y_2010": "158580"
  },
  {
    "id": "389",
    "y_2010": "99127"
  },
  {
    "id": "390",
    "y_2010": "136819"
  },
  {
    "id": "391",
    "y_2010": "226846"
  },
  {
    "id": "392",
    "y_2010": "649041"
  },
  {
    "id": "393",
    "y_2010": "193610"
  },
  {
    "id": "394",
    "y_2010": "159476"
  },
  {
    "id": "395",
    "y_2010": "186549"
  },
  {
    "id": "396",
    "y_2010": "182280"
  },
  {
    "id": "397",
    "y_2010": "174067"
  },
  {
    "id": "398",
    "y_2010": "140993"
  },
  {
    "id": "399",
    "y_2010": "243778"
  },
  {
    "id": "400",
    "y_2010": "287315"
  },
  {
    "id": "401",
    "y_2010": "179805"
  },
  {
    "id": "402",
    "y_2010": "191510"
  },
  {
    "id": "403",
    "y_2010": "280758"
  },
  {
    "id": "404",
    "y_2010": "114417"
  },
  {
    "id": "405",
    "y_2010": "156682"
  },
  {
    "id": "406",
    "y_2010": "242914"
  },
  {
    "id": "407",
    "y_2010": "196907"
  },
  {
    "id": "408",
    "y_2010": "208064"
  },
  {
    "id": "409",
    "y_2010": "713932"
  },
  {
    "id": "410",
    "y_2010": "246384"
  },
  {
    "id": "411",
    "y_2010": "148928"
  },
  {
    "id": "412",
    "y_2010": "243194"
  },
  {
    "id": "413",
    "y_2010": "274970"
  },
  {
    "id": "416",
    "y_2010": "145046"
  },
  {
    "id": "417",
    "y_2010": "191536"
  },
  {
    "id": "418",
    "y_2010": "332344"
  },
  {
    "id": "419",
    "y_2010": "271933"
  },
  {
    "id": "420",
    "y_2010": "261821"
  },
  {
    "id": "421",
    "y_2010": "208821"
  },
  {
    "id": "422",
    "y_2010": "139047"
  },
  {
    "id": "423",
    "y_2010": "222235"
  },
  {
    "id": "424",
    "y_2010": "443121"
  },
  {
    "id": "425",
    "y_2010": "286979"
  },
  {
    "id": "426",
    "y_2010": "180910"
  },
  {
    "id": "428",
    "y_2010": "199801"
  },
  {
    "id": "430",
    "y_2010": "156728"
  },
  {
    "id": "431",
    "y_2010": "130362"
  },
  {
    "id": "432",
    "y_2010": "207335"
  },
  {
    "id": "433",
    "y_2010": "269269"
  },
  {
    "id": "434",
    "y_2010": "317038"
  },
  {
    "id": "435",
    "y_2010": "208845"
  },
  {
    "id": "436",
    "y_2010": "149991"
  },
  {
    "id": "437",
    "y_2010": "199395"
  },
  {
    "id": "438",
    "y_2010": "265789"
  },
  {
    "id": "442",
    "y_2010": "108309"
  },
  {
    "id": "443",
    "y_2010": "217750"
  },
  {
    "id": "444",
    "y_2010": "145387"
  },
  {
    "id": "445",
    "y_2010": "196642"
  },
  {
    "id": "446",
    "y_2010": "171179"
  },
  {
    "id": "447",
    "y_2010": "170401"
  },
  {
    "id": "448",
    "y_2010": "223205"
  },
  {
    "id": "449",
    "y_2010": "717086"
  },
  {
    "id": "450",
    "y_2010": "282998"
  },
  {
    "id": "451",
    "y_2010": "439426"
  },
  {
    "id": "452",
    "y_2010": "176523"
  },
  {
    "id": "453",
    "y_2010": "122785"
  },
  {
    "id": "454",
    "y_2010": "246529"
  },
  {
    "id": "455",
    "y_2010": "223751"
  },
  {
    "id": "456",
    "y_2010": "247954"
  },
  {
    "id": "457",
    "y_2010": "264039"
  },
  {
    "id": "458",
    "y_2010": "216050"
  },
  {
    "id": "459",
    "y_2010": "161971"
  },
  {
    "id": "460",
    "y_2010": "166616"
  },
  {
    "id": "462",
    "y_2010": "206074"
  },
  {
    "id": "463",
    "y_2010": "191759"
  },
  {
    "id": "464",
    "y_2010": "265827"
  },
  {
    "id": "465",
    "y_2010": "200591"
  },
  {
    "id": "466",
    "y_2010": "181880"
  },
  {
    "id": "467",
    "y_2010": "211265"
  },
  {
    "id": "468",
    "y_2010": "325732"
  },
  {
    "id": "469",
    "y_2010": "358663"
  },
  {
    "id": "470",
    "y_2010": "367486"
  },
  {
    "id": "471",
    "y_2010": "161218"
  },
  {
    "id": "472",
    "y_2010": "493211"
  },
  {
    "id": "473",
    "y_2010": "189779"
  },
  {
    "id": "474",
    "y_2010": "283178"
  },
  {
    "id": "475",
    "y_2010": "440464"
  }
]